Metadata-Version: 2.1
Name: discord-apii-py
Version: 0.0.1
Summary: discord api wrapper made by zt#7380
Home-page: UNKNOWN
Author: zt | github.com/populated
Author-email: <emailspammerv1@gmail.com>
License: UNKNOWN
Keywords: python,discord,vanity
Platform: UNKNOWN
Classifier: Intended Audience :: Developers
Classifier: Programming Language :: Python :: 3
Classifier: Operating System :: Microsoft :: Windows
